fabric_data_guard/__init__.py
fabric_data_guard/checkpoint.py
fabric_data_guard/consts.py
fabric_data_guard/core.py
fabric_data_guard/display.py
fabric_data_guard/expectations.py
fabric_data_guard/result_parser.py
fabric_data_guard/utils.py
fabric_data_guard/validation.py
fabric_data_guard-0.0.3.dist-info/METADATA
fabric_data_guard-0.0.3.dist-info/WHEEL
fabric_data_guard-0.0.3.dist-info/RECORD
