Metadata-Version: 2.1
Name: fabric-data-guard
Version: 0.0.3
Summary: A library for data quality checks in Microsoft Fabric using Great Expectations
Home-page: https://github.com/birdid/fabric-data-guard
Author: DOUCOURE, DIOULA
Author-email: diioula.doucoure@gmail.com
Requires-Python: >=3.10,<3.12
Classifier: Programming Language :: Python :: 3
Classifier: Programming Language :: Python :: 3.10
Classifier: Programming Language :: Python :: 3.11
Requires-Dist: azure-core (>=1.31.0,<2.0.0)
Requires-Dist: azure-storage-blob (>=12.23.1,<13.0.0)
Requires-Dist: delta-spark (>=3.2.1,<4.0.0)
Requires-Dist: dummy-notebookutils (>=1.5.3,<2.0.0)
Requires-Dist: great-expectations (>=1.1.2,<2.0.0)
Requires-Dist: ipython (==8.14.0)
Requires-Dist: pandas (>=2.1,<3.0)
Requires-Dist: pyjwt (>=2.9.0,<3.0.0)
Requires-Dist: pyspark (>=3.5.3,<4.0.0)
Requires-Dist: pytest (>=8.3.3,<9.0.0)
Requires-Dist: semantic-link (>=0.8.0,<0.9.0)
Project-URL: Repository, https://github.com/birdid/fabric-data-guard
